TB2Jflows/__init__.py
TB2Jflows/ase_siesta.py
TB2Jflows/auto_siesta_TB2J.py
TB2Jflows/run_abacus.py
tb2jflows-0.2.dist-info/licenses/LICENSE
tb2jflows-0.2.dist-info/METADATA
tb2jflows-0.2.dist-info/WHEEL
tb2jflows-0.2.dist-info/top_level.txt
tb2jflows-0.2.dist-info/RECORD
