Metadata-Version: 2.4
Name: TB2Jflows
Version: 0.2
Summary: TB2Jflows: Workflows for automatically calculation of exchange parameters using TB2J
Author: Xu He
Author-email: mailhexu@gmail.com
License: BSD-2-clause
Classifier: Development Status :: 3 - Alpha
Classifier: Programming Language :: Python :: 3
Classifier: Operating System :: OS Independent
Classifier: Intended Audience :: Science/Research
Classifier: Topic :: Scientific/Engineering :: Chemistry
Classifier: Topic :: Scientific/Engineering :: Physics
Classifier: License :: OSI Approved :: BSD License
Requires-Python: >=3.6
License-File: LICENSE
Requires-Dist: TB2J
Requires-Dist: ase
Requires-Dist: sisl
Requires-Dist: pyDFTutils
Dynamic: author
Dynamic: author-email
Dynamic: classifier
Dynamic: description
Dynamic: license
Dynamic: license-file
Dynamic: requires-dist
Dynamic: requires-python
Dynamic: summary
